XTS_Tradehull/Connect.py
XTS_Tradehull/Exception.py
XTS_Tradehull/XTS_Tradehull.py
XTS_Tradehull/__init__.py
XTS_Tradehull-1.0.2.dist-info/METADATA
XTS_Tradehull-1.0.2.dist-info/WHEEL
XTS_Tradehull-1.0.2.dist-info/top_level.txt
XTS_Tradehull-1.0.2.dist-info/RECORD
