Metadata-Version: 2.1
Name: XTS_Tradehull
Version: 1.0.2
Summary: A XTS Codebase from TradeHull
Home-page: https://github.com/TradeHull/XTS_Tradehull
Author: TradeHull
Author-email: contact.tradehull@gmail.com
Classifier: Programming Language :: Python :: 3
Classifier: License :: OSI Approved :: MIT License
Classifier: Operating System :: OS Independent
Requires-Python: >=3.8
Requires-Dist: mibian>=0.1.3
Requires-Dist: numpy>=1.24.4
Requires-Dist: pandas>=2.0.3
Requires-Dist: pytz>=2024.1
Requires-Dist: requests>=2.32.3
Requires-Dist: python-socketio>=5.12.1
Requires-Dist: websocket-client>=1.8.0
Requires-Dist: websockets>=13.1
